fairtool/__init__.py
fairtool/__main__.py
fairtool/analyze.py
fairtool/cli.py
fairtool/export.py
fairtool/parse.py
fairtool/summarize.py
fairtool/visualize.py
fairtool-0.1.0.dist-info/licenses/LICENSE
fairtool-0.1.0.dist-info/METADATA
fairtool-0.1.0.dist-info/WHEEL
fairtool-0.1.0.dist-info/entry_points.txt
fairtool-0.1.0.dist-info/top_level.txt
fairtool-0.1.0.dist-info/RECORD
